samplepypackagexxx/__init__.py
samplepypackagexxx/add.py
samplepypackagexxx/subtract.py
samplepypackagexxx/extras/__init__.py
samplepypackagexxx/extras/divide.py
samplepypackagexxx/extras/multiply.py
samplepypackagexxx-0.0.8.dist-info/METADATA
samplepypackagexxx-0.0.8.dist-info/WHEEL
samplepypackagexxx-0.0.8.dist-info/top_level.txt
samplepypackagexxx-0.0.8.dist-info/RECORD
