Metadata-Version: 2.1
Name: samplepypackagexxx
Version: 0.0.8
Summary: sample package
Author: Julian Amin
Author-email: julian.amin@infor.com
Keywords: samplepackage
